[
  {
    "id": "True dragon, Itrenog_0000",
    "content": "Profile\n바칼을 따르는 네 명의 강력한 용인 중 하나로, 단단한 비늘만으로 다른 세 용인과 어깨를 나란히 했다. 본래 용족의 비늘이 웬만한 무기로는 뚫을 수 없을 정도로 단단하지만, 이트레녹의 비늘은 그 궤를 달리하며 이를 바탕으로 과격한 전투를 즐긴다. 용족 중에서도 소문난 전투광으로 알려져 있지만, 한 가지 특이한 점은 생사의 기로에 선 긴장감을 즐기거나\n강자와의 결투에서 깨달음을 얻고자 함이 아닌, 자신의 힘을 증명하고 약자를 짓밟기 위한 싸움에서만 투기를 드러낸다. 즉, 결투에서 자신의 죽음은 상정하지 않으며 패배한다면 언제라도 또 다른 결투를 위해 도망칠 준비가 되어있다. 역사의 기록에는 천계인들에게는 결코 뚫을 수 없는 비늘을 가진 용인이었으나,\n기계 혁명 당시 천계인들의 과학력에 의해 마침내 비늘이 뚫린 채 장렬한 최후를 맞이한 것으로 기록되어 있다. Story\n쿠웅-\n메마른 대지에 진동이 울려 퍼졌다. 잠깐 동안이나마 ‘병기’라고 불렸던 ‘고철’은 힘없이 무너져내렸고,\n그렇게 이 황량한 사막에는 또 하나의 쓰레기가 늘었다. 고철 위에 올라탄 채 이트레녹은 머리를 사납게 헝클었다.\n“재미없군.”\n이트레녹은 따로 자신의 영역을 두지 않았다. 자신에게 체통과 품위를 익힐 필요가 있다며 시답잖은 소릴 하는 녀석이 그분께 천계인들의 저택을 하사받을 때에도,\n음침하기 짝이 없는 땅꼬마 녀석이 거대한 숲 하나를 통째로 집어삼킬 때에도,\n자신의 충성심을 보이는 것이 삶의 전부인 녀석이 스스로 문지기를 자처할 때에도,\n이트레녹은 그저 여기저기 방랑하며 강해 보이는 녀석에게 싸움을 걸어댈 뿐이었다. 이따금씩 그분의 명령을 위해 궁에 드나들긴 했지만, 명령들은 언제나 귀찮고 지루한 것들 뿐이었고,\n이번에도 그러한 명령을 받을 거라 생각했다. 하지만 적어도, 이번에 들은 명령만큼은 이트레녹의 가슴을 쿵쾅거리게 했다. 낯선 곳에서 온 자들이라니...! 그분께서 신경 쓸 정도의 존재라면 도대체 얼마나 강한 것일까. 만약 그들을 만난다면, 결코 쉽게 죽이지 않을 것이다. 분노라는 거친 감정이 이트레녹은 썩 나쁘지 않았다. 버러지 같은 것들이 감히 자신에게 모욕적인 말을 쏟아내는 것이 기분이 나쁘기도 하였지만\n종국에 자신이 무력했음을 실감하고 절망하는 녀석들을 보고 있노라면 자신이 얼마나 강한지를 새삼 깨닫게 해주었고,\n그때의 고양감은 마치 자신이 전능하다고 느껴지기까지 했다. 그러니까, 자신의 흥미가 다할 때까지, 천천히, 아주 천천히 그 힘을 다 내보일 수 있도록 세심하게 다룰 것이다. 전투가 길어져 그들이 지친다면, 다시 힘을 낼 수 있도록 가장 소중한 것을 빼앗을 것이다. 인간이란 본디 그런 것에 분노하는 이해할 수 없는 종족이니까.\n...라는 생각을 잠시 동안 했었다. 부푸는 마음을 안고 철의 무덤으로 달려왔건만, 보이는 건 고철과 고철이 될 예정인 것들뿐이었다. 이따금씩 같잖은 유기물들이 무언가를 열심히 쏴대는 것이 어렴풋이 느껴지긴 했지만\n그마저도 이내 쓰러진 고철 밑에선 잠잠해졌다. 이제 ‘철의 무덤’을 ‘철의 바다’라고 불러야 하지 않을까 고민이 들 때쯤이 되어서야\n이트레녹은 신경조차 쓰지 않았던 유기물들 중에 강자가 숨어있지 않을까 하는 기대를 품기 시작했고\n그마저도 얼마 지나지 않아 자신의 헛된 바람임을 깨달았다. 기잉-\n익숙한 기계의 기동음이 또다시 들려왔다. 아아... 저 녀석도 또 지루하기 짝이 없는 녀석이겠지. 이트레녹은 높이 도약했고, 이내 지축을 뒤흔들며 또 하나의 고철을 만들어냈다. 제발, 부디 여기로 오너라. 낯선 곳에서 온 자들아. 내가 기다린 만큼 너희는 날 즐겁게 해주어야 할 테니. 목소리 녹음: 성우 조민수",
    "metadata": {
      "chunk_index": 0,
      "chunk_tokens": 1896,
      "total_chunks": 1,
      "keywords": [
        "True dragon, Itrenog"
      ]
    }
  }
]